mmrazor/__init__.py
mmrazor/version.py
mmrazor/.mim/model-index.yml
mmrazor/.mim/configs/_base_/datasets/mmcls/cifar100_bs16_auto_aug.py
mmrazor/.mim/configs/_base_/datasets/mmcls/pipelines/auto_aug_cifar.py
mmrazor/.mim/configs/_base_/nas_backbones/attentive_mobilenetv3_supernet.py
mmrazor/.mim/configs/_base_/nas_backbones/darts_supernet.py
mmrazor/.mim/configs/_base_/nas_backbones/dsnas_shufflenet_supernet.py
mmrazor/.mim/configs/_base_/nas_backbones/ofa_mobilenetv3_supernet.py
mmrazor/.mim/configs/_base_/nas_backbones/spos_mobilenet_supernet.py
mmrazor/.mim/configs/_base_/nas_backbones/spos_shufflenet_supernet.py
mmrazor/.mim/configs/_base_/settings/cifar10_darts_subnet.py
mmrazor/.mim/configs/_base_/settings/cifar10_darts_supernet.py
mmrazor/.mim/configs/_base_/settings/imagenet_bs1024_dsnas.py
mmrazor/.mim/configs/_base_/settings/imagenet_bs1024_spos.py
mmrazor/.mim/configs/_base_/settings/imagenet_bs2048_AdamW.py
mmrazor/.mim/configs/_base_/settings/imagenet_bs2048_autoslim.py
mmrazor/.mim/configs/_base_/settings/imagenet_bs2048_autoslim_pil.py
mmrazor/.mim/configs/_base_/settings/imagenet_bs2048_bignas.py
mmrazor/.mim/configs/_base_/settings/imagenet_bs2048_dmcp.py
mmrazor/.mim/configs/_base_/settings/imagenet_bs2048_ofa.py
mmrazor/.mim/configs/_base_/vanilla_models/wrn16_2_cifar10.py
mmrazor/.mim/configs/distill/mmcls/abloss/abloss_logits_resnet50_resnet18_8xb32_in1k.py
mmrazor/.mim/configs/distill/mmcls/abloss/abloss_pretrain_backbone_resnet50_resnet18_8xb32_in1k.py
mmrazor/.mim/configs/distill/mmcls/abloss/metafile.yml
mmrazor/.mim/configs/distill/mmcls/byot/byot_resnet18_8xb16_cifar100.py
mmrazor/.mim/configs/distill/mmcls/byot/metafile.yml
mmrazor/.mim/configs/distill/mmcls/crd/crd_neck_r50_r18_8xb16_cifar10.py
mmrazor/.mim/configs/distill/mmcls/crd/datasets/crd_cifar10_bs16.py
mmrazor/.mim/configs/distill/mmcls/dafl/dafl_logits_resnet34_resnet18_8xb256_cifar10.py
mmrazor/.mim/configs/distill/mmcls/dafl/metafile.yml
mmrazor-1.0.0.dist-info/LICENSE
mmrazor-1.0.0.dist-info/METADATA
mmrazor-1.0.0.dist-info/WHEEL
mmrazor-1.0.0.dist-info/top_level.txt
mmrazor-1.0.0.dist-info/RECORD
