Metadata-Version: 2.1
Name: mmrazor
Version: 1.0.0
Summary: OpenMMLab Model Compression Toolbox and Benchmark
Home-page: https://github.com/open-mmlab/mmrazor
Author: MMRazor Contributors
Author-email: openmmlab@gmail.com
License: Apache License 2.0
Keywords: computer vision,model compression
Platform: UNKNOWN
Classifier: Development Status :: 4 - Beta
Classifier: License :: OSI Approved :: Apache Software License
Classifier: Operating System :: OS Independent
Classifier: Programming Language :: Python :: 3
Classifier: Programming Language :: Python :: 3.5
Classifier: Programming Language :: Python :: 3.6
Classifier: Programming Language :: Python :: 3.7
Classifier: Programming Language :: Python :: 3.8
Classifier: Programming Language :: Python :: 3.9
Classifier: Topic :: Scientific/Engineering :: Artificial Intelligence
Requires-Dist: ordered-set
Requires-Dist: typing-extensions ; python_version < "3.8"
Provides-Extra: all
Requires-Dist: pydacefit ; extra == 'all'
Requires-Dist: pySOT (==0.2.3) ; extra == 'all'
Requires-Dist: scipy ; extra == 'all'
Requires-Dist: timm ; extra == 'all'
Requires-Dist: ordered-set ; extra == 'all'
Requires-Dist: coverage ; extra == 'all'
Requires-Dist: flake8 ; extra == 'all'
Requires-Dist: interrogate ; extra == 'all'
Requires-Dist: isort (==4.3.21) ; extra == 'all'
Requires-Dist: nbconvert ; extra == 'all'
Requires-Dist: nbformat ; extra == 'all'
Requires-Dist: numpy (<1.24.0) ; extra == 'all'
Requires-Dist: onnx ; extra == 'all'
Requires-Dist: pytest ; extra == 'all'
Requires-Dist: xdoctest (>=0.10.0) ; extra == 'all'
Requires-Dist: yapf ; extra == 'all'
Requires-Dist: typing-extensions ; (python_version < "3.8") and extra == 'all'
Provides-Extra: mim
Requires-Dist: mmcv (>=2.0.0rc1) ; extra == 'mim'
Requires-Dist: mmengine (<1.0.0,>=0.1.0) ; extra == 'mim'
Provides-Extra: optional
Requires-Dist: pydacefit ; extra == 'optional'
Requires-Dist: pySOT (==0.2.3) ; extra == 'optional'
Requires-Dist: scipy ; extra == 'optional'
Requires-Dist: timm ; extra == 'optional'
Provides-Extra: tests
Requires-Dist: coverage ; extra == 'tests'
Requires-Dist: flake8 ; extra == 'tests'
Requires-Dist: interrogate ; extra == 'tests'
Requires-Dist: isort (==4.3.21) ; extra == 'tests'
Requires-Dist: nbconvert ; extra == 'tests'
Requires-Dist: nbformat ; extra == 'tests'
Requires-Dist: numpy (<1.24.0) ; extra == 'tests'
Requires-Dist: onnx ; extra == 'tests'
Requires-Dist: pytest ; extra == 'tests'
Requires-Dist: xdoctest (>=0.10.0) ; extra == 'tests'
Requires-Dist: yapf ; extra == 'tests'
